maltorch/__init__.py
maltorch/adv/__init__.py
maltorch/adv/evasion/__init__.py
maltorch/adv/evasion/backend_attack.py
maltorch/adv/evasion/base_optim_attack_creator.py
maltorch/adv/evasion/content_shift.py
maltorch/adv/evasion/extend_dos.py
maltorch/adv/evasion/fulldos.py
maltorch/adv/evasion/gamma_section_injection.py
maltorch/adv/evasion/gradfree_attack.py
maltorch/adv/evasion/gradient_attack.py
maltorch/adv/evasion/padding.py
maltorch/adv/evasion/partialdos.py
maltorch/adv/evasion/section_injection.py
maltorch/data/__init__.py
maltorch/data/loader.py
maltorch/data_processing/__init__.py
maltorch/data_processing/dynamic_random_drs_preprocessing.py
maltorch/data_processing/dynamic_sequential_drs_preprocessing.py
maltorch/data_processing/e2e_preprocessor.py
maltorch/data_processing/ember_preprocessing.py
maltorch/data_processing/fixed_size_chunk_drs_preprocessing.py
maltorch/data_processing/grayscale_preprocessing.py
maltorch/data_processing/k_partition_drs_preprocessing.py
maltorch/data_processing/majority_voting_postprocessing.py
maltorch/data_processing/rs_preprocessing.py
maltorch/data_processing/rsdel_preprocessing.py
maltorch/data_processing/sigmoid_postprocessor.py
maltorch/data_processing/thrember_preprocessing.py
maltorch/data_processing/dynamic/__init__.py
maltorch/data_processing/dynamic/constants.py
maltorch/data_processing/dynamic/emulation.py
maltorch/data_processing/dynamic/normalization.py
maltorch/data_processing/dynamic/tokenization.py
maltorch/datasets/__init__.py
maltorch/datasets/binary_dataset.py
maltorch/datasets/dynamic_drs_dataset.py
maltorch/datasets/dynamic_random_drs_dataset.py
maltorch/datasets/dynamic_sequential_drs_dataset.py
maltorch/datasets/fixed_size_chunk_drs_dataset.py
maltorch/datasets/grayscale_dataset.py
maltorch/datasets/k_partition_drs_dataset.py
maltorch/datasets/random_chunk_sampler.py
maltorch/datasets/rs_dataset.py
maltorch/datasets/rsdel_dataset.py
maltorch/initializers/__init__.py
maltorch-0.3.dist-info/METADATA
maltorch-0.3.dist-info/WHEEL
maltorch-0.3.dist-info/top_level.txt
maltorch-0.3.dist-info/RECORD
